<?xml version='1.0' encoding='UTF-8' standalone='yes' ?><hierarchy rotation="0"><node index="0" text="" resource-id="" class="android.widget.FrameLayout" package="app.zeniptv.mobile" content-desc="" checkable="false" checked="false" clickable="false" enabled="true" focusable="false" focused="false" scrollable="false" long-clickable="false" password="false" selected="false" bounds="[0,0][1080,2220]"><node index="0" text="" resource-id="" class="android.widget.LinearLayout" package="app.zeniptv.mobile" content-desc="" checkable="false" checked="false" clickable="false" enabled="true" focusable="false" focused="false" scrollable="false" long-clickable="false" password="false" selected="false" bounds="[0,0][1080,2154]"><node index="0" text="" resource-id="android:id/content" class="android.widget.FrameLayout" package="app.zeniptv.mobile" content-desc="" checkable="false" checked="false" clickable="false" enabled="true" focusable="false" focused="false" scrollable="false" long-clickable="false" password="false" selected="false" bounds="[0,0][1080,2154]"><node index="0" text="" resource-id="" class="android.widget.FrameLayout" package="app.zeniptv.mobile" content-desc="" checkable="false" checked="false" clickable="false" enabled="true" focusable="true" focused="true" scrollable="false" long-clickable="false" password="false" selected="false" bounds="[0,0][1080,2154]"><node index="0" text="" resource-id="" class="android.view.View" package="app.zeniptv.mobile" content-desc="" checkable="false" checked="false" clickable="false" enabled="true" focusable="false" focused="false" scrollable="false" long-clickable="false" password="false" selected="false" bounds="[0,0][1080,2154]"><node index="0" text="" resource-id="" class="android.view.View" package="app.zeniptv.mobile" content-desc="" checkable="false" checked="false" clickable="false" enabled="true" focusable="false" focused="false" scrollable="false" long-clickable="false" password="false" selected="false" bounds="[0,0][1080,2154]"><node index="0" text="" resource-id="" class="android.view.View" package="app.zeniptv.mobile" content-desc="" checkable="false" checked="false" clickable="false" enabled="true" focusable="false" focused="false" scrollable="false" long-clickable="false" password="false" selected="false" bounds="[0,0][1080,2154]"><node index="0" text="" resource-id="" class="android.view.View" package="app.zeniptv.mobile" content-desc="" checkable="false" checked="false" clickable="false" enabled="true" focusable="false" focused="false" scrollable="false" long-clickable="false" password="false" selected="false" bounds="[0,0][1080,2154]"><node index="0" text="" resource-id="" class="android.view.View" package="app.zeniptv.mobile" content-desc="" checkable="false" checked="false" clickable="false" enabled="true" focusable="false" focused="false" scrollable="false" long-clickable="false" password="false" selected="false" bounds="[0,0][1080,220]"><node index="0" text="" resource-id="" class="android.view.View" package="app.zeniptv.mobile" content-desc="Zen Player" checkable="false" checked="false" clickable="false" enabled="true" focusable="true" focused="false" scrollable="false" long-clickable="false" password="false" selected="false" bounds="[44,105][326,182]" /><node NAF="true" index="1" text="" resource-id="" class="android.widget.Button" package="app.zeniptv.mobile" content-desc="" checkable="false" checked="false" clickable="true" enabled="true" focusable="true" focused="false" scrollable="false" long-clickable="false" password="false" selected="false" bounds="[816,77][948,209]" /><node NAF="true" index="2" text="" resource-id="" class="android.widget.Button" package="app.zeniptv.mobile" content-desc="" checkable="false" checked="false" clickable="true" enabled="true" focusable="true" focused="false" scrollable="false" long-clickable="false" password="false" selected="false" bounds="[948,77][1080,209]" /></node><node NAF="true" index="1" text="" resource-id="" class="android.widget.EditText" package="app.zeniptv.mobile" content-desc="" checkable="false" checked="false" clickable="true" enabled="true" focusable="true" focused="false" scrollable="false" long-clickable="false" password="false" selected="false" bounds="[33,253][1047,407]" /><node index="2" text="" resource-id="" class="android.view.View" package="app.zeniptv.mobile" content-desc="Tapez pour rechercher" checkable="false" checked="false" clickable="false" enabled="true" focusable="true" focused="false" scrollable="false" long-clickable="false" password="false" selected="false" bounds="[342,1160][738,1215]" /><node index="3" text="" resource-id="" class="android.view.View" package="app.zeniptv.mobile" content-desc="" checkable="false" checked="false" clickable="false" enabled="true" focusable="false" focused="false" scrollable="false" long-clickable="false" password="false" selected="false" bounds="[0,1934][1080,2154]"><node index="0" text="" resource-id="" class="android.view.View" package="app.zeniptv.mobile" content-desc="" checkable="false" checked="false" clickable="false" enabled="true" focusable="false" focused="false" scrollable="false" long-clickable="false" password="false" selected="false" bounds="[0,1934][1080,2154]"><node index="0" text="" resource-id="" class="android.widget.Button" package="app.zeniptv.mobile" content-desc="TV&#10;Tab 1 of 4" checkable="false" checked="false" clickable="true" enabled="true" focusable="true" focused="false" scrollable="false" long-clickable="false" password="false" selected="false" bounds="[0,1934][270,2154]" /><node index="1" text="" resource-id="" class="android.widget.Button" package="app.zeniptv.mobile" content-desc="Films&#10;Tab 2 of 4" checkable="false" checked="false" clickable="true" enabled="true" focusable="true" focused="false" scrollable="false" long-clickable="false" password="false" selected="false" bounds="[270,1934][540,2154]" /><node index="2" text="" resource-id="" class="android.widget.Button" package="app.zeniptv.mobile" content-desc="Séries&#10;Tab 3 of 4" checkable="false" checked="false" clickable="true" enabled="true" focusable="true" focused="false" scrollable="false" long-clickable="false" password="false" selected="false" bounds="[540,1934][810,2154]" /><node index="3" text="" resource-id="" class="android.widget.Button" package="app.zeniptv.mobile" content-desc="Recherche&#10;Tab 4 of 4" checkable="false" checked="false" clickable="true" enabled="true" focusable="true" focused="false" scrollable="false" long-clickable="false" password="false" selected="true" bounds="[810,1934][1080,2154]" /></node></node></node></node></node></node></node></node></node><node index="1" text="" resource-id="android:id/navigationBarBackground" class="android.view.View" package="app.zeniptv.mobile" content-desc="" checkable="false" checked="false" clickable="false" enabled="true" focusable="false" focused="false" scrollable="false" long-clickable="false" password="false" selected="false" bounds="[0,2154][1080,2220]" /></node></hierarchy>